grabngo/__init__.py
grabngo/grabngo.py
grabngo-0.1.1.dist-info/AUTHORS.rst
grabngo-0.1.1.dist-info/LICENSE
grabngo-0.1.1.dist-info/METADATA
grabngo-0.1.1.dist-info/WHEEL
grabngo-0.1.1.dist-info/top_level.txt
grabngo-0.1.1.dist-info/RECORD
