Metadata-Version: 2.1
Name: grabngo
Version: 0.1.1
Summary: Optimal Permutation-based SGD Data Sampler for PyTorch
Author-email: garywei944 <garywei944@gmail.com>
License: Apache Software License 2.0
Project-URL: Homepage, https://www.garywei.dev
Project-URL: Documentation, https://readthedocs.org
Project-URL: Repository, https://github.com/garywei944/grabngo
Project-URL: Changelog, https://github.com/garywei944/grabngo/blob/main/HISTORY.rst
Project-URL: Bug_Tracker, https://github.com/GarlGuo/GraB-lib/issues
Keywords: GraB,data-permutation,PyTorch,dataloader,sampler
Classifier: Development Status :: 2 - Pre-Alpha
Classifier: Intended Audience :: Developers
Classifier: License :: OSI Approved :: Apache Software License
Classifier: Natural Language :: English
Classifier: Operating System :: OS Independent
Classifier: Programming Language :: Python :: 3
Classifier: Programming Language :: Python :: 3.10
Requires-Python: >=3.10
License-File: LICENSE
License-File: AUTHORS.rst
Requires-Dist: torch >=2.0.0
Requires-Dist: numpy
Requires-Dist: pandas
Requires-Dist: absl-py
Requires-Dist: overrides
